{"capturableKeys":["Trigo","Ball"],"capturableIDs":["Trigo","Ball"],"capturableAmount":[61,30],"molecularKeys":["Molecule Ricardo","Molecule Hongo"],"molecularIDs":["Molecule Ricardo","Molecule Hongo"],"molecularAmount":[211,248],"monstersHouse":[{"baseId":0,"monsterName":"ElCubo","level":1,"currentXP":25,"currentHealth":43.0,"isUsed":true,"isStarter":true},{"baseId":1,"monsterName":"Hongui","level":4,"currentXP":65,"currentHealth":45.0,"isUsed":true,"isStarter":true},{"baseId":2,"monsterName":"Magic","level":4,"currentXP":15,"currentHealth":1.0,"isUsed":false,"isStarter":false},{"baseId":3,"monsterName":"Ricardo","level":4,"currentXP":0,"currentHealth":1.0,"isUsed":true,"isStarter":false}],"monstersDungeon":[{"baseId":1,"monsterName":"Hongui","level":4,"currentXP":100,"currentHealth":27.0,"isUsed":true,"isStarter":true},{"baseId":0,"monsterName":"ElCubo","level":4,"currentXP":125,"currentHealth":30.0,"isUsed":true,"isStarter":true},{"baseId":2,"monsterName":"Magic","level":4,"currentXP":50,"currentHealth":32.0,"isUsed":true,"isStarter":false},{"baseId":3,"monsterName":"Ricardo","level":4,"currentXP":35,"currentHealth":45.0,"isUsed":true,"isStarter":false},{"baseId":0,"monsterName":"","level":0,"currentXP":0,"currentHealth":0.0,"isUsed":false,"isStarter":false},{"baseId":0,"monsterName":"","level":0,"currentXP":0,"currentHealth":0.0,"isUsed":false,"isStarter":false}],"bestiary":[{"monsterName":"Monkey Helper","viewed":true,"wasFriend":false},{"monsterName":"Hongui","viewed":true,"wasFriend":true},{"monsterName":"ElCubo","viewed":false,"wasFriend":true},{"monsterName":"Magic","viewed":false,"wasFriend":true},{"monsterName":"Ricardo","viewed":false,"wasFriend":true},{"monsterName":"Dolly","viewed":false,"wasFriend":true}],"eggs":[{"id":0,"monsterName":"Hongui","currentPoints":3.0,"itemProgress":[0,0,0,0]}],"runesDungeon":[],"upgradesDungeon":[]}